out_of_domain/__init__.py
out_of_domain/feature_extraction.py
out_of_domain/similarity_check.py
out_of_domain_library-0.2.dist-info/METADATA
out_of_domain_library-0.2.dist-info/WHEEL
out_of_domain_library-0.2.dist-info/top_level.txt
out_of_domain_library-0.2.dist-info/RECORD
