Metadata-Version: 2.1
Name: out-of-domain-library
Version: 0.2
Summary: A library for out-of-domain tasks.
Home-page: https://github.com/suraj385/out_of_domain_library
Author: Suraj Gautam
Author-email: beoingsuraz3385@gmail.com
Classifier: Programming Language :: Python :: 3
Classifier: License :: OSI Approved :: MIT License
Classifier: Operating System :: OS Independent
Requires-Python: >=3.6
Requires-Dist: torch >=1.7.1
Requires-Dist: torchvision >=0.8.2
Requires-Dist: Pillow >=8.0.1
Requires-Dist: numpy >=1.19.4
Requires-Dist: scikit-learn >=0.23.2
